typtr/__init__.py
typtr/base.py
typtr/cli.py
typtr/cstyle.py
typtr/java.py
typtr/js.py
typtr/typescanner.py
typtr-0.1.0.dist-info/LICENSE
typtr-0.1.0.dist-info/METADATA
typtr-0.1.0.dist-info/WHEEL
typtr-0.1.0.dist-info/entry_points.txt
typtr-0.1.0.dist-info/top_level.txt
typtr-0.1.0.dist-info/RECORD
