Metadata-Version: 2.1
Name: typtr
Version: 0.1.0
Summary: A transpiler for an idiomatic subset of typed Python into semantically similar object-oriented languages.
Author-email: Niklas Lindström <lindstream@gmail.com>
License: ISC License
Classifier: License :: OSI Approved :: ISC License (ISCL)
Classifier: Operating System :: OS Independent
Classifier: Programming Language :: Python :: 3
Classifier: Topic :: Software Development
Classifier: Typing :: Typed
License-File: LICENSE
